{
  "openapi": "3.0.1",
  "info": {
    "title": "BENewsFeed",
    "version": "1.0"
  },
  "paths": {
    "/api/Articles": {
      "get": {
        "tags": [
          "Articles"
        ],
        "parameters": [
          {
            "name": "category",
            "in": "query",
            "schema": {
              "type": "string"
            }
          },
          {
            "name": "sourceId",
            "in": "query",
            "schema": {
              "type": "integer",
              "format": "int32"
            }
          }
        ],
        "responses": {
          "200": {
            "description": "OK"
          }
        }
      }
    },
    "/api/Articles/{id}": {
      "get": {
        "tags": [
          "Articles"
        ],
        "parameters": [
          {
            "name": "id",
            "in": "path",
            "required": true,
            "schema": {
              "type": "integer",
              "format": "int32"
            }
          }
        ],
        "responses": {
          "200": {
            "description": "OK"
          }
        }
      }
    },
    "/api/Articles/refresh": {
      "post": {
        "tags": [
          "Articles"
        ],
        "responses": {
          "200": {
            "description": "OK"
          }
        }
      }
    },
    "/api/Articles/search": {
      "get": {
        "tags": [
          "Articles"
        ],
        "parameters": [
          {
            "name": "key",
            "in": "query",
            "schema": {
              "type": "string"
            }
          }
        ],
        "responses": {
          "200": {
            "description": "OK"
          }
        }
      }
    },
    "/api/Categories": {
      "get": {
        "tags": [
          "Categories"
        ],
        "responses": {
          "200": {
            "description": "OK"
          }
        }
      }
    },
    "/api/Sources": {
      "get": {
        "tags": [
          "Sources"
        ],
        "responses": {
          "200": {
            "description": "OK"
          }
        }
      }
    },
    "/WeatherForecast": {
      "get": {
        "tags": [
          "WeatherForecast"
        ],
        "operationId": "GetWeatherForecast",
        "responses": {
          "200": {
            "description": "OK",
            "content": {
              "text/plain": {
                "schema": {
                  "type": "array",
                  "items": {
                    "$ref": "#/components/schemas/WeatherForecast"
                  }
                }
              },
              "application/json": {
                "schema": {
                  "type": "array",
                  "items": {
                    "$ref": "#/components/schemas/WeatherForecast"
                  }
                }
              },
              "text/json": {
                "schema": {
                  "type": "array",
                  "items": {
                    "$ref": "#/components/schemas/WeatherForecast"
                  }
                }
              }
            }
          }
        }
      }
    }
  },
  "components": {
    "schemas": {
      "WeatherForecast": {
        "type": "object",
        "properties": {
          "date": {
            "type": "string",
            "format": "date"
          },
          "temperatureC": {
            "type": "integer",
            "format": "int32"
          },
          "temperatureF": {
            "type": "integer",
            "format": "int32",
            "readOnly": true
          },
          "summary": {
            "type": "string",
            "nullable": true
          }
        },
        "additionalProperties": false
      }
    }
  }
}